hello_world_sandhya/app.py
hello_world3108-1.0.5.2.dist-info/LICENSE
hello_world3108-1.0.5.2.dist-info/METADATA
hello_world3108-1.0.5.2.dist-info/WHEEL
hello_world3108-1.0.5.2.dist-info/entry_points.txt
hello_world3108-1.0.5.2.dist-info/top_level.txt
hello_world3108-1.0.5.2.dist-info/RECORD
